<?xml version="1.0" encoding="utf-8"?>
<LanguageData>

  <!-- Railgun Component -->

  <Railgun_Component.label>Компоненты рейлгана</Railgun_Component.label>
  <Railgun_Component.description>Основные детали рельсового оружия.</Railgun_Component.description>


  <!-- Power module basic -->

  <Power_basic.label>Базовый модуль питания Авали</Power_basic.label>
  <Power_basic.description>Основной источник энергии для оружия и брони Авали.</Power_basic.description>


  <!-- Power module advensed -->

  <Power_adv.label>Продвинутый модуль питания Авали</Power_adv.label>
  <Power_adv.description>Улучшенный энергетический модуль, необходимый для создания мощного оружия и брони авали.</Power_adv.description>


</LanguageData>